{
    "#raritydef": "%hash_47748ff97b0f469c",
    "#pingvo": "#hash_6b8874a19007433b",
    "#hash_ff1750b480636dc9": 1,
    "#maxattachments": 1,
    "#maxcount": 1,
    "#hash_359e971d09addafc": "#hash_d40e9c698c76a57f",
    "#titlestring": "&WEAPON/SM_MPAPA7",
    "#worldmodel": "weapon_wm_sm_mpapa7_brprop_nophys",
    "#attachmentslots": [
        {
            "#forced": 1,
            "#excludelist": [
                {
                    "#attachment": "arscope_nvg01"
                },
                {
                    "#attachment": "arscope_nvg02"
                }
            ],
            "#includelist": [
                {
                    "#attachment": "iw9_minireddot02_tall"
                },
                {
                    "#attachment": "iw9_minireddot03_tall"
                },
                {
                    "#attachment": "iw9_minireddot04_tall"
                }
            ],
            "#slot": "scope"
        }
    ],
    "#descstring": "&WEAPON/SM_MPAPA7",
    "#ref": "iw9_sm_mpapa7",
    "#inventoryslot": "Weapon",
    "#dropsfx": "#hash_23339f32a414a102",
    "#lootidtype": "weapon",
    "#hash_8464122fb6575536": 1,
    "#type": "weapon",
    "#subtype": "sm",
    "#baseweapon": "iw9_sm_mpapa7_mp",
    "#hash_95d6d970efccc96d": "common_unrestricted",
    "#pickupsfx": "#hash_b5059413ad647316",
    "#inventorytype": "Loadout",
    "#icon": "hud_icon_weapon_sm_mpapa7",
    "#scriptable": "%hash_fff8a53221a7aec",
    "#lifetime": 300,
    "#denialsfx": "#hash_afeb34a87e316add",
    "#typestring": "&MP/BR_TYPE_SM"
}