{
    "#id": "in_game_hardware_alert_icons",
    "#description": "&OPTIONS/INGAME_HARDWARE_ALERT_ICONS_DESC",
    "#image": "image_options_hardwarealerts",
    "#labels": [
        {
            "#reference": "&MENU/OFF"
        },
        {
            "#reference": "&MENU/ON"
        }
    ],
    "#hash_a20785232d9c4057": "displayHardwareAlertIcon",
    "#hash_58d61dc3eef940dc": "GENERAL",
    "#type": "ToggleButton",
    "#hash_6158fef2a07d0451": [
        {
            "#hash_a085177b45ffc883": 1,
            "#type": "PLATFORM"
        }
    ],
    "#name": "&OPTIONS/INGAME_HARDWARE_ALERT_ICONS_TITLE"
}