{
    "#id": "sound_mono_amount",
    "#description": "&OPTIONS/MONO_AMOUNT_DESC",
    "#hash_ea45bc5a5e9ac302": 1,
    "#hash_a20785232d9c4057": "SoundMonoAmount",
    "#hash_58d61dc3eef940dc": "AUDIO",
    "#hash_15963d81d6fd6dac": 100,
    "#hash_5460095effa6dac7": 0,
    "#hash_df2c0bf51d7fb6ea": 1,
    "#type": "SliderBarWithEditBox",
    "#name": "&OPTIONS/MONO_AMOUNT",
    "#hash_5d30c39665a86e5d": "&OPTIONS/MONO_AMOUNT_DISABLED_DESC",
    "#hash_66f8d4776faaa59c": 1,
    "#hash_c55c746ff4d8929b": 1
}